dmathtools/__init__.py
dmathtools/LogicCalculator/LogicCalculator.py
dmathtools/LogicCalculator/__init__.py
dmathtools/LogicCalculator/compileUi.py
dmathtools/LogicCalculator/gui.py
dmathtools/LogicCalculator/gui.ui
dmathtools-1.2.dist-info/LICENSE
dmathtools-1.2.dist-info/METADATA
dmathtools-1.2.dist-info/WHEEL
dmathtools-1.2.dist-info/top_level.txt
dmathtools-1.2.dist-info/RECORD
